tornado_tryton/__init__.py
tornado_tryton/tornado_tryton.py
tornado_tryton-1.0.2.dist-info/LICENSE
tornado_tryton-1.0.2.dist-info/METADATA
tornado_tryton-1.0.2.dist-info/WHEEL
tornado_tryton-1.0.2.dist-info/top_level.txt
tornado_tryton-1.0.2.dist-info/RECORD
