Metadata-Version: 2.1
Name: tornado-tryton
Version: 1.0.2
Summary: Adds Tryton support to Tornado application.
Home-page: https://github.com/TinKurbatoff/tornado-tryton
Author: James Sparc
Author-email: jimmysparc@gmail.com
License: UNKNOWN
Project-URL: Bug Tracker, https://github.com/TinKurbatoff/tornado-tryton/issues
Platform: UNKNOWN
Classifier: Programming Language :: Python :: 3
Classifier: License :: OSI Approved :: GNU General Public License (GPL)
Classifier: Operating System :: OS Independent
Requires-Python: >=3.6
